django_countries_geoextent/__init__.py
django_countries_geoextent/admin.py
django_countries_geoextent/apps.py
django_countries_geoextent/countries.json
django_countries_geoextent/countries.py
django_countries_geoextent/models.py
django_countries_geoextent/tests.py
django_countries_geoextent/utils.py
django_countries_geoextent/views.py
django_countries_geoextent/migrations/__init__.py
django_countries_geoextent-0.0.1.dist-info/METADATA
django_countries_geoextent-0.0.1.dist-info/WHEEL
django_countries_geoextent-0.0.1.dist-info/entry_points.txt
django_countries_geoextent-0.0.1.dist-info/top_level.txt
django_countries_geoextent-0.0.1.dist-info/RECORD
